ratinabox/Agent.py
ratinabox/Environment.py
ratinabox/Neurons.py
ratinabox/README.md
ratinabox/__init__.py
ratinabox/utils.py
ratinabox/contribs/FieldOfViewNeurons.py
ratinabox/contribs/NeuralNetworkNeurons.py
ratinabox/contribs/PhasePrecessingPlaceCells.py
ratinabox/contribs/PlaneWaveNeurons.py
ratinabox/contribs/README.md
ratinabox/contribs/SubAgent.py
ratinabox/contribs/SuccessorFeatures.py
ratinabox/contribs/TaskEnvironment.py
ratinabox/contribs/ThetaSequenceAgent.py
ratinabox/contribs/ValueNeuron.py
ratinabox/contribs/__init__.py
ratinabox/data/README.md
ratinabox/data/__init__.py
ratinabox/data/rat.png
ratinabox/data/sargolini.npz
ratinabox/data/tanni.npz
ratinabox-1.15.3.dist-info/LICENSE
ratinabox-1.15.3.dist-info/METADATA
ratinabox-1.15.3.dist-info/WHEEL
ratinabox-1.15.3.dist-info/top_level.txt
ratinabox-1.15.3.dist-info/RECORD
