Metadata-Version: 2.1
Name: ratinabox
Version: 1.15.3
Summary: RatInABox: A package for simulating spatial navigation and  spatial representation neural data in continuous 2D environments
Author: Tom George
Author-email: tomgeorge1@btinternet.com
License: MIT
Project-URL: Documentation, https://github.com/RatInABox-Lab/RatInABox
Project-URL: Source, https://github.com/RatInABox-Lab/RatInABox
Project-URL: Tracker, https://github.com/RatInABox-Lab/RatInABox/issues
Platform: any
Classifier: License :: OSI Approved :: MIT License
Classifier: Operating System :: OS Independent
Classifier: Programming Language :: Python :: 3
Requires-Python: >=3.7
Provides-Extra: test
Provides-Extra: gymnasium
License-File: LICENSE
